cage_json_extractor/__init__.py
cage_json_extractor/cage_json_extractor.py
cage_json_extractor/extract_cages.py
cage_json_extractor/py.typed
cage_json_extractor-1.0.0.dist-info/METADATA
cage_json_extractor-1.0.0.dist-info/WHEEL
cage_json_extractor-1.0.0.dist-info/entry_points.txt
cage_json_extractor-1.0.0.dist-info/top_level.txt
cage_json_extractor-1.0.0.dist-info/RECORD
