Metadata-Version: 2.1
Name: cage-json-extractor
Version: 1.0.0
Maintainer-email: Lukas Turcani <lukasturcani93@gmail.com>
Project-URL: github, https://github.com/lukasturcani/cage_json_extractor
Requires-Python: >=3.11
Requires-Dist: rdkit
Requires-Dist: atomlite
Requires-Dist: stk
Provides-Extra: dev
Requires-Dist: black ; extra == 'dev'
Requires-Dist: ruff ; extra == 'dev'
Requires-Dist: mypy ; extra == 'dev'
Requires-Dist: build ; extra == 'dev'
Requires-Dist: twine ; extra == 'dev'
